Metadata-Version: 2.4
Name: fastcomments-python
Version: 0.0.1
Summary: FastComments Python SDK - A SDK for interacting with the FastComments API
Author-email: FastComments <support@fastcomments.com>
License-Expression: MIT
Project-URL: Homepage, https://github.com/fastcomments/fastcomments-python
Project-URL: Documentation, https://docs.fastcomments.com
Project-URL: Repository, https://github.com/fastcomments/fastcomments-python
Project-URL: Issues, https://github.com/fastcomments/fastcomments-python/issues
Classifier: Development Status :: 3 - Alpha
Classifier: Intended Audience :: Developers
Classifier: Programming Language :: Python :: 3
Classifier: Programming Language :: Python :: 3.8
Classifier: Programming Language :: Python :: 3.9
Classifier: Programming Language :: Python :: 3.10
Classifier: Programming Language :: Python :: 3.11
Classifier: Programming Language :: Python :: 3.12
Requires-Python: >=3.8
License-File: LICENSE
Requires-Dist: urllib3>=1.25.3
Requires-Dist: python-dateutil>=2.8.2
Requires-Dist: pydantic>=2.0.0
Requires-Dist: typing-extensions>=4.0.0
Provides-Extra: dev
Requires-Dist: pytest>=7.0.0; extra == "dev"
Requires-Dist: pytest-cov>=4.0.0; extra == "dev"
Requires-Dist: pytest-asyncio>=0.21.0; extra == "dev"
Requires-Dist: mypy>=1.0.0; extra == "dev"
Requires-Dist: flake8>=6.0.0; extra == "dev"
Requires-Dist: black>=23.0.0; extra == "dev"
Dynamic: license-file
